{
  "connector": "authipay",
  "flows": {
    "authenticate": {
      "default": {
        "status": "not_implemented"
      }
    },
    "authorize": {
      "Ach": {
        "status": "not_implemented",
        "error": "This step has not been implemented for: Only card payments are supported"
      },
      "Affirm": {
        "status": "not_implemented",
        "error": "This step has not been implemented for: Only card payments are supported"
      },
      "Afterpay": {
        "status": "not_implemented",
        "error": "This step has not been implemented for: Only card payments are supported"
      },
      "ApplePay": {
        "status": "not_implemented",
        "error": "This step has not been implemented for: Only card payments are supported"
      },
      "ApplePayDecrypted": {
        "status": "not_implemented",
        "error": "This step has not been implemented for: Only card payments are supported"
      },
      "Bacs": {
        "status": "not_implemented",
        "error": "This step has not been implemented for: Only card payments are supported"
      },
      "Becs": {
        "status": "not_implemented",
        "error": "This step has not been implemented for: Only card payments are supported"
      },
      "Blik": {
        "status": "not_implemented",
        "error": "This step has not been implemented for: Only card payments are supported"
      },
      "Card": {
        "status": "supported",
        "proto_request": {
          "merchant_transaction_id": "probe_txn_001",
          "amount": {
            "minor_amount": 1000,
            "currency": "USD"
          },
          "payment_method": {
            "card": {
              "card_number": "4111111111111111",
              "card_exp_month": "03",
              "card_exp_year": "2030",
              "card_cvc": "737",
              "card_holder_name": "John Doe"
            }
          },
          "capture_method": "AUTOMATIC",
          "address": {
            "billing_address": {}
          },
          "auth_type": "NO_THREE_DS",
          "return_url": "https://example.com/return"
        },
        "sample": {
          "url": "https://prod.emea.api.fiservapps.com/sandbox/ipp/payments-gateway/v2/payments",
          "method": "Post",
          "headers": {
            "api-key": "probe_key",
            "client-request-id": "00000000-0000-0000-0000-000000000000",
            "content-type": "application/json",
            "message-signature": "cHJvYmVfa2V5OnByb2JlX3NlY3JldA==",
            "timestamp": "0000000000",
            "via": "HyperSwitch"
          },
          "body": "{\"requestType\":\"PaymentCardSaleTransaction\",\"merchantTransactionId\":\"probe_txn_001\",\"transactionAmount\":{\"total\":10.0,\"currency\":\"USD\"},\"order\":{\"orderId\":\"probe_txn_001\"},\"paymentMethod\":{\"paymentCard\":{\"number\":\"4111111111111111\",\"expiryDate\":{\"month\":\"03\",\"year\":\"30\"},\"securityCode\":\"737\"}}}"
        }
      },
      "GooglePay": {
        "status": "not_implemented",
        "error": "This step has not been implemented for: Only card payments are supported"
      },
      "GooglePayDecrypted": {
        "status": "not_implemented",
        "error": "This step has not been implemented for: Only card payments are supported"
      },
      "Ideal": {
        "status": "not_implemented",
        "error": "This step has not been implemented for: Only card payments are supported"
      },
      "Klarna": {
        "status": "not_implemented",
        "error": "This step has not been implemented for: Only card payments are supported"
      },
      "PaypalRedirect": {
        "status": "not_implemented",
        "error": "This step has not been implemented for: Only card payments are supported"
      },
      "SamsungPay": {
        "status": "not_implemented",
        "error": "This step has not been implemented for: Only card payments are supported"
      },
      "Sepa": {
        "status": "not_implemented",
        "error": "This step has not been implemented for: Only card payments are supported"
      },
      "UpiCollect": {
        "status": "not_implemented",
        "error": "This step has not been implemented for: Only card payments are supported"
      }
    },
    "capture": {
      "default": {
        "status": "supported",
        "proto_request": {
          "merchant_capture_id": "probe_capture_001",
          "connector_transaction_id": "probe_connector_txn_001",
          "amount_to_capture": {
            "minor_amount": 1000,
            "currency": "USD"
          }
        },
        "sample": {
          "url": "https://prod.emea.api.fiservapps.com/sandbox/ipp/payments-gateway/v2/payments/probe_connector_txn_001",
          "method": "Post",
          "headers": {
            "api-key": "probe_key",
            "client-request-id": "00000000-0000-0000-0000-000000000000",
            "content-type": "application/json",
            "message-signature": "cHJvYmVfa2V5OnByb2JlX3NlY3JldA==",
            "timestamp": "0000000000",
            "via": "HyperSwitch"
          },
          "body": "{\"requestType\":\"PostAuthTransaction\",\"transactionAmount\":{\"total\":10.0,\"currency\":\"USD\"}}"
        }
      }
    },
    "create_access_token": {
      "default": {
        "status": "not_implemented"
      }
    },
    "create_customer": {
      "default": {
        "status": "not_implemented"
      }
    },
    "create_order": {
      "default": {
        "status": "not_implemented"
      }
    },
    "create_session_token": {
      "default": {
        "status": "not_implemented"
      }
    },
    "dispute_accept": {
      "default": {
        "status": "not_implemented"
      }
    },
    "dispute_defend": {
      "default": {
        "status": "not_implemented"
      }
    },
    "dispute_submit_evidence": {
      "default": {
        "status": "not_implemented"
      }
    },
    "get": {
      "default": {
        "status": "supported",
        "proto_request": {
          "merchant_transaction_id": "probe_merchant_txn_001",
          "connector_transaction_id": "probe_connector_txn_001",
          "amount": {
            "minor_amount": 1000,
            "currency": "USD"
          }
        },
        "sample": {
          "url": "https://prod.emea.api.fiservapps.com/sandbox/ipp/payments-gateway/v2/payments/probe_connector_txn_001",
          "method": "Get",
          "headers": {
            "api-key": "probe_key",
            "client-request-id": "00000000-0000-0000-0000-000000000000",
            "content-type": "application/json",
            "message-signature": "cHJvYmVfa2V5OnByb2JlX3NlY3JldA==",
            "timestamp": "0000000000",
            "via": "HyperSwitch"
          },
          "body": null
        }
      }
    },
    "post_authenticate": {
      "default": {
        "status": "not_implemented"
      }
    },
    "pre_authenticate": {
      "default": {
        "status": "not_implemented"
      }
    },
    "proxied_authorize": {
      "default": {
        "status": "error",
        "error": "Missing card number"
      }
    },
    "proxied_setup_recurring": {
      "default": {
        "status": "error",
        "error": "Customer acceptance is missing"
      }
    },
    "recurring_charge": {
      "default": {
        "status": "not_implemented"
      }
    },
    "refund": {
      "default": {
        "status": "supported",
        "proto_request": {
          "merchant_refund_id": "probe_refund_001",
          "connector_transaction_id": "probe_connector_txn_001",
          "payment_amount": 1000,
          "refund_amount": {
            "minor_amount": 1000,
            "currency": "USD"
          },
          "reason": "customer_request"
        },
        "sample": {
          "url": "https://prod.emea.api.fiservapps.com/sandbox/ipp/payments-gateway/v2/payments/probe_connector_txn_001",
          "method": "Post",
          "headers": {
            "api-key": "probe_key",
            "client-request-id": "00000000-0000-0000-0000-000000000000",
            "content-type": "application/json",
            "message-signature": "cHJvYmVfa2V5OnByb2JlX3NlY3JldA==",
            "timestamp": "0000000000",
            "via": "HyperSwitch"
          },
          "body": "{\"requestType\":\"ReturnTransaction\",\"transactionAmount\":{\"total\":10.0,\"currency\":\"USD\"},\"comments\":\"customer_request\"}"
        }
      }
    },
    "reverse": {
      "default": {
        "status": "not_implemented"
      }
    },
    "setup_recurring": {
      "default": {
        "status": "not_implemented"
      }
    },
    "tokenize": {
      "default": {
        "status": "not_implemented"
      }
    },
    "tokenized_authorize": {
      "default": {
        "status": "not_implemented",
        "error": "This step has not been implemented for: Only card payments are supported"
      }
    },
    "tokenized_setup_recurring": {
      "default": {
        "status": "error",
        "error": "Future usage must be specified"
      }
    },
    "void": {
      "default": {
        "status": "supported",
        "proto_request": {
          "merchant_void_id": "probe_void_001",
          "connector_transaction_id": "probe_connector_txn_001"
        },
        "sample": {
          "url": "https://prod.emea.api.fiservapps.com/sandbox/ipp/payments-gateway/v2/payments/probe_connector_txn_001",
          "method": "Post",
          "headers": {
            "api-key": "probe_key",
            "client-request-id": "00000000-0000-0000-0000-000000000000",
            "content-type": "application/json",
            "message-signature": "cHJvYmVfa2V5OnByb2JlX3NlY3JldA==",
            "timestamp": "0000000000",
            "via": "HyperSwitch"
          },
          "body": "{\"requestType\":\"VoidPreAuthTransactions\"}"
        }
      }
    }
  }
}